jupyter_rfb/__init__.py
jupyter_rfb/_jpg.py
jupyter_rfb/_png.py
jupyter_rfb/_utils.py
jupyter_rfb/_version.py
jupyter_rfb/events.py
jupyter_rfb/widget.py
jupyter_rfb-0.5.4.data/data/share/jupyter/labextensions/jupyter_rfb/package.json
jupyter_rfb-0.5.4.data/data/share/jupyter/labextensions/jupyter_rfb/static/420.ea335d7dbbcfd3a24eeb.js
jupyter_rfb-0.5.4.data/data/share/jupyter/labextensions/jupyter_rfb/static/493.b23cace24a93a8aa68b5.js
jupyter_rfb-0.5.4.data/data/share/jupyter/labextensions/jupyter_rfb/static/remoteEntry.17c1fdd55c78860e7992.js
jupyter_rfb-0.5.4.data/data/share/jupyter/labextensions/jupyter_rfb/static/style.js
jupyter_rfb-0.5.4.data/data/share/jupyter/labextensions/jupyter_rfb/static/third-party-licenses.json
jupyter_rfb-0.5.4.data/data/etc/jupyter/nbconfig/notebook.d/jupyter_rfb.json
jupyter_rfb-0.5.4.data/data/share/jupyter/labextensions/jupyter_rfb/install.json
jupyter_rfb-0.5.4.dist-info/METADATA
jupyter_rfb-0.5.4.dist-info/WHEEL
jupyter_rfb-0.5.4.dist-info/licenses/LICENSE
jupyter_rfb-0.5.4.dist-info/RECORD
