Metadata-Version: 2.4
Name: jupyter-rfb
Version: 0.5.4
Summary: Remote Frame Buffer for Jupyter
Project-URL: Homepage, https://github.com/vispy/jupyter_rfb
Project-URL: Documentation, https://jupyter-rfb.readthedocs.io/en/stable/
Project-URL: Repository, https://github.com/vispy/jupyter_rfb
Author: Almar Klein
License: MIT License
License-File: LICENSE
Keywords: ipython,jupyter,remote frame buffer,visualization,widgets
Classifier: Development Status :: 4 - Beta
Classifier: Framework :: IPython
Classifier: Intended Audience :: Developers
Classifier: Intended Audience :: Science/Research
Classifier: Topic :: Multimedia :: Graphics
Requires-Python: >=3.9
Requires-Dist: ipywidgets<9,>=7.6.0
Requires-Dist: numpy
Provides-Extra: build
Requires-Dist: build; extra == 'build'
Requires-Dist: hatch-jupyter-builder; extra == 'build'
Requires-Dist: hatchling; extra == 'build'
Requires-Dist: twine; extra == 'build'
Provides-Extra: dev
Requires-Dist: build; extra == 'dev'
Requires-Dist: hatch-jupyter-builder; extra == 'dev'
Requires-Dist: hatchling; extra == 'dev'
Requires-Dist: ipywidgets; extra == 'dev'
Requires-Dist: nbsphinx; extra == 'dev'
Requires-Dist: numpy; extra == 'dev'
Requires-Dist: pre-commit; extra == 'dev'
Requires-Dist: pytest; extra == 'dev'
Requires-Dist: ruff; extra == 'dev'
Requires-Dist: simplejpeg; extra == 'dev'
Requires-Dist: sphinx; extra == 'dev'
Requires-Dist: twine; extra == 'dev'
Provides-Extra: docs
Requires-Dist: ipywidgets; extra == 'docs'
Requires-Dist: nbsphinx; extra == 'docs'
Requires-Dist: numpy; extra == 'docs'
Requires-Dist: sphinx; extra == 'docs'
Provides-Extra: lint
Requires-Dist: pre-commit; extra == 'lint'
Requires-Dist: ruff; extra == 'lint'
Provides-Extra: tests
Requires-Dist: pytest; extra == 'tests'
Requires-Dist: simplejpeg; extra == 'tests'
